insoundz_api/VERSION
insoundz_api/__init__.py
insoundz_api/api.py
insoundz_api/enhancer.py
insoundz_api/helpers.py
insoundz_api/version.py
insoundz_api-0.1.21.dist-info/LICENSE
insoundz_api-0.1.21.dist-info/METADATA
insoundz_api-0.1.21.dist-info/WHEEL
insoundz_api-0.1.21.dist-info/top_level.txt
insoundz_api-0.1.21.dist-info/RECORD
