Metadata-Version: 2.1
Name: insoundz_api
Version: 0.1.21
Summary: Insoundz API client implementation         to produce audio enhancement.
Home-page: https://github.com/InSoundz/insoundz-api
License: MIT
Project-URL: Source Code, https://github.com/InSoundz/insoundz-api/tree/main/insoundz_api
Classifier: Operating System :: OS Independent
Classifier: Intended Audience :: Developers
Classifier: License :: OSI Approved :: MIT License
Classifier: Programming Language :: Python :: 3
Classifier: Programming Language :: Python :: 3.7
Classifier: Programming Language :: Python :: 3.8
Classifier: Programming Language :: Python :: 3.9
Classifier: Programming Language :: Python :: 3.10
Requires-Python: >=3.7
License-File: LICENSE
Requires-Dist: requests
Requires-Dist: tqdm
Requires-Dist: halo
Requires-Dist: validators
